jim_test_server/__init__.py
jim_test_server/jim_module.py
jim_test_server/metaclass.py
jim_test_server/serv_form.py
jim_test_server/server.py
jim_test_server/storage.py
jim_test_server/log/__init__.py
jim_test_server/log/log_deco.py
jim_test_server/log/server_log_config.py
jim_test_server-0.2.dist-info/METADATA
jim_test_server-0.2.dist-info/WHEEL
jim_test_server-0.2.dist-info/top_level.txt
jim_test_server-0.2.dist-info/RECORD
