Metadata-Version: 2.1
Name: jim-test-server
Version: 0.2
Summary: JSON Instant Messenger Server part
Home-page: https://github.com/Yephim/JIM_sever
Author: Efim Sudov
Author-email: Efim.Sudov@nw.rt.ru
License: UNKNOWN
Platform: UNKNOWN
